subscript/__init__.py
subscript/version.py
subscript/bjobsusers/__init__.py
subscript/bjobsusers/bjobsusers.py
subscript/casegen_upcars/__init__.py
subscript/casegen_upcars/casegen_upcars.py
subscript/casegen_upcars/model.py
subscript/casegen_upcars/udf.py
subscript/casegen_upcars/udf_arg_parser.py
subscript/check_swatinit/__init__.py
subscript/check_swatinit/check_swatinit.py
subscript/check_swatinit/constants.py
subscript/check_swatinit/pillarmodel.py
subscript/check_swatinit/plotter.py
subscript/convert_grid_format/__init__.py
subscript/convert_grid_format/convert_grid_format.py
subscript/create_date_files/__init__.py
subscript/create_date_files/create_date_files.py
subscript/csv2ofmvol/__init__.py
subscript/csv2ofmvol/csv2ofmvol.py
subscript/csv_merge/__init__.py
subscript/csv_merge/csv_merge.py
subscript/csv_stack/__init__.py
subscript/csv_stack/csv_stack.py
subscript/eclcompress/__init__.py
subscript/eclcompress/allowlist.py
subscript/eclcompress/eclcompress.py
subscript/ecldiff2roff/__init__.py
subscript/ecldiff2roff/ecldiff2roff.py
subscript/field_statistics/__init__.py
subscript/field_statistics/field_statistics.py
subscript/fmu_copy_revision/__init__.py
subscript/fmu_copy_revision/fmu_copy_revision.py
subscript/fmuobs/__init__.py
subscript/fmuobs/fmuobs.py
subscript/fmuobs/parsers.py
subscript/fmuobs/util.py
subscript/fmuobs/writers.py
subscript/grav_subs_maps/__init__.py
subscript/grav_subs_maps/grav_subs_maps.py
subscript/grav_subs_points/__init__.py
subscript/grav_subs_points/grav_subs_points.py
subscript/hook_implementations/__init__.py
subscript/hook_implementations/forward_model_steps.py
subscript/interp_relperm/__init__.py
subscript/interp_relperm/interp_relperm.py
subscript/legacy/duf
subscript/legacy/eclmanual
subscript/legacy/ertwatch
subscript/legacy/list_rms_usage
subscript/legacy/nosim
subscript/legacy/runeclipse
subscript/merge_rft_ertobs/__init__.py
subscript/merge_rft_ertobs/merge_rft_ertobs.py
subscript/merge_unrst_files/__init__.py
subscript-1.14.5.dist-info/licenses/LICENSE
subscript-1.14.5.dist-info/METADATA
subscript-1.14.5.dist-info/WHEEL
subscript-1.14.5.dist-info/entry_points.txt
subscript-1.14.5.dist-info/top_level.txt
subscript-1.14.5.dist-info/RECORD
