Metadata-Version: 2.4
Name: subscript
Version: 1.14.5
Summary: Equinor's collection of subsurface reservoir modelling scripts
Author-email: Equinor <rnyb@equinor.com>
License-Expression: GPL-3.0-only
Project-URL: Homepage, https://github.com/equinor/subscript
Project-URL: Repository, https://github.com/equinor/subscript
Project-URL: Documentation, https://equinor.github.io/subscript
Keywords: energy,subsurface,reservoir,scientific,engineering
Classifier: Development Status :: 5 - Production/Stable
Classifier: Intended Audience :: Science/Research
Classifier: Topic :: Scientific/Engineering
Classifier: Topic :: Scientific/Engineering :: Physics
Classifier: Topic :: Software Development :: Libraries
Classifier: Topic :: Utilities
Classifier: Operating System :: POSIX :: Linux
Classifier: Programming Language :: Python :: 3.11
Classifier: Programming Language :: Python :: 3.12
Classifier: Programming Language :: Python :: 3.13
Classifier: Natural Language :: English
Requires-Python: >=3.11
License-File: LICENSE
Requires-Dist: resdata
Requires-Dist: res2df
Requires-Dist: ert>=10.2.0b13
Requires-Dist: fmu-tools
Requires-Dist: grid3d_maps
Requires-Dist: jinja2
Requires-Dist: matplotlib
Requires-Dist: numpy
Requires-Dist: opm>=2023.04
Requires-Dist: pandas
Requires-Dist: pydantic
Requires-Dist: pyscal
Requires-Dist: pyyaml
Requires-Dist: scipy
Requires-Dist: seaborn
Requires-Dist: xtgeo
Provides-Extra: tests
Requires-Dist: mypy; extra == "tests"
Requires-Dist: pytest; extra == "tests"
Requires-Dist: pytest-cov; extra == "tests"
Requires-Dist: pytest-mock; extra == "tests"
Requires-Dist: pytest-mpl; extra == "tests"
Requires-Dist: pytest-xdist; extra == "tests"
Requires-Dist: rstcheck; extra == "tests"
Requires-Dist: rstcheck-core; extra == "tests"
Requires-Dist: ruff; extra == "tests"
Requires-Dist: types-Jinja2; extra == "tests"
Requires-Dist: types-PyYAML; extra == "tests"
Requires-Dist: types-python-dateutil; extra == "tests"
Requires-Dist: pandas-stubs; extra == "tests"
Requires-Dist: types-seaborn; extra == "tests"
Requires-Dist: scipy-stubs; extra == "tests"
Provides-Extra: docs
Requires-Dist: autoapi; extra == "docs"
Requires-Dist: sphinx; extra == "docs"
Requires-Dist: sphinx-argparse; extra == "docs"
Requires-Dist: sphinx-autodoc-typehints; extra == "docs"
Requires-Dist: sphinx-copybutton; extra == "docs"
Requires-Dist: sphinx-togglebutton; extra == "docs"
Requires-Dist: sphinx_rtd_theme; extra == "docs"
Dynamic: license-file
